LICENSE
MANIFEST.in
README.rst
requirements.txt
setup.py
ua_api_utils.egg-info/PKG-INFO
ua_api_utils.egg-info/SOURCES.txt
ua_api_utils.egg-info/dependency_links.txt
ua_api_utils.egg-info/entry_points.txt
ua_api_utils.egg-info/not-zip-safe
ua_api_utils.egg-info/requires.txt
ua_api_utils.egg-info/top_level.txt
ua_utils/__init__.py
ua_utils/_version.py
ua_utils/cli.py
ua_utils/commands.py