Metadata-Version: 1.1
Name: ua-api-utils
Version: 0.1.1
Summary: Utilities for working with Urban Airship's APIs
Home-page: https://github.com/urbanairship/ua-api-utils
Author: Michael Schurter
Author-email: schmichael@urbanairship.com
License: APLv2
Platform: UNKNOWN
Classifier: License :: OSI Approved :: Apache Software License
